pyfmt/__init__.py
pyfmt/cli.py
pyfmt/pyfmt.py
pyfmt_svtter-0.1.0.dist-info/AUTHORS.rst
pyfmt_svtter-0.1.0.dist-info/LICENSE
pyfmt_svtter-0.1.0.dist-info/METADATA
pyfmt_svtter-0.1.0.dist-info/WHEEL
pyfmt_svtter-0.1.0.dist-info/entry_points.txt
pyfmt_svtter-0.1.0.dist-info/top_level.txt
pyfmt_svtter-0.1.0.dist-info/RECORD
