Metadata-Version: 2.1
Name: pyfmt-svtter
Version: 0.1.0
Summary: Format code use black, autoflake, isort
Home-page: https://github.com/svtter/pyfmt
Author: svtter
Author-email: svtter@qq.com
License: MIT license
Keywords: pyfmt
Platform: UNKNOWN
Classifier: Development Status :: 2 - Pre-Alpha
Classifier: Intended Audience :: Developers
Classifier: License :: OSI Approved :: MIT License
Classifier: Natural Language :: English
Classifier: Programming Language :: Python :: 3
Classifier: Programming Language :: Python :: 3.5
Classifier: Programming Language :: Python :: 3.6
Classifier: Programming Language :: Python :: 3.7
Classifier: Programming Language :: Python :: 3.8
Requires-Python: >=3.5
Requires-Dist: Click (>=7.0)
Requires-Dist: black
Requires-Dist: isort (>=4.0)
Requires-Dist: autoflake
